<?xml version="1.0" encoding="UTF-8"?>
<objects serializationModel="Studio.02.03.00">
	<object class="AudioFile" id="{8a4463c4-3240-4664-82ba-748bbd6570d2}">
		<property name="assetPath">
			<value>Sound FX/Applause/Large Crowd Applause 02.wav</value>
		</property>
		<property name="isStreaming">
			<value>true</value>
		</property>
		<property name="frequencyInKHz">
			<value>44.0999985</value>
		</property>
		<property name="channelCount">
			<value>2</value>
		</property>
		<property name="length">
			<value>10.310158730158729</value>
		</property>
		<relationship name="masterAssetFolder">
			<destination>{0dde74d6-2506-40f2-9e5c-0d88018e7cc7}</destination>
		</relationship>
	</object>
</objects>
